COPYING
COPYING.LESSER
LICENSE
celestical/__init__.py
celestical/api/__init__.py
celestical/api/api/__init__.py
celestical/api/api/app_api.py
celestical/api/api/auth_api.py
celestical/api/api/default_api.py
celestical/api/api/openseats_api.py
celestical/api/api/payment_api.py
celestical/api/api/product_api.py
celestical/api/api/stacy_api.py
celestical/api/api/users_api.py
celestical/api/api/utils_api.py
celestical/api/api_client.py
celestical/api/api_response.py
celestical/api/configuration.py
celestical/api/exceptions.py
celestical/api/models/__init__.py
celestical/api/models/app.py
celestical/api/models/app_removal.py
celestical/api/models/bearer_response.py
celestical/api/models/body_reset_forgot_password_auth_forgot_password_post.py
celestical/api/models/body_reset_reset_password_auth_reset_password_post.py
celestical/api/models/body_verify_request_token_auth_request_verify_token_post.py
celestical/api/models/body_verify_verify_auth_verify_post.py
celestical/api/models/client_id.py
celestical/api/models/client_secret.py
celestical/api/models/compose.py
celestical/api/models/deploy.py
celestical/api/models/detail.py
celestical/api/models/error_model.py
celestical/api/models/first_creator.py
celestical/api/models/grant_type.py
celestical/api/models/http_validation_error.py
celestical/api/models/is_active.py
celestical/api/models/is_superuser.py
celestical/api/models/is_verified.py
celestical/api/models/missing_apps.py
celestical/api/models/missing_images.py
celestical/api/models/name.py
celestical/api/models/payment_status.py
celestical/api/models/product.py
celestical/api/models/product_order.py
celestical/api/models/public_key.py
celestical/api/models/stack.py
celestical/api/models/the_hundred.py
celestical/api/models/transaction_status.py
celestical/api/models/uploaded_image.py
celestical/api/models/user_create.py
celestical/api/models/user_read.py
celestical/api/models/validation_error.py
celestical/api/models/version_check.py
celestical/api/py.typed
celestical-1.3.15.dist-info/COPYING
celestical-1.3.15.dist-info/COPYING.LESSER
celestical-1.3.15.dist-info/LICENSE
celestical-1.3.15.dist-info/METADATA
celestical-1.3.15.dist-info/WHEEL
celestical-1.3.15.dist-info/entry_points.txt
celestical-1.3.15.dist-info/RECORD
