Metadata-Version: 2.3
Name: celestical
Version: 1.3.15
Summary: A CLI to interact with the Celestical Serverless Cloud.
License: LGPL-3.0-or-later
Author: Red Boumghar
Author-email: red@celestical.eu
Requires-Python: >=3.10,<4.0
Classifier: License :: OSI Approved :: GNU Lesser General Public License v3 (LGPLv3)
Classifier: License :: OSI Approved :: GNU Lesser General Public License v3 or later (LGPLv3+)
Classifier: Operating System :: OS Independent
Classifier: Programming Language :: Python :: 3
Classifier: Programming Language :: Python :: 3.10
Classifier: Programming Language :: Python :: 3.11
Classifier: Programming Language :: Python :: 3.12
Classifier: Programming Language :: Python :: 3.13
Requires-Dist: aenum (>=3.1.11)
Requires-Dist: docker (>=7.0.0,<8.0.0)
Requires-Dist: icecream (>=2.1.3,<3.0.0)
Requires-Dist: packaging (>=25.0,<26.0)
Requires-Dist: paramiko (>=3.3.1,<4.0.0)
Requires-Dist: prettytable (>=3.9.0,<4.0.0)
Requires-Dist: pydantic (>=2.11)
Requires-Dist: python-dateutil (>=2.5.3)
Requires-Dist: pyyaml (>=6.0.1,<7.0.0)
Requires-Dist: requests (>=2.32.4,<3.0.0)
Requires-Dist: rich (>=14.0.0,<15.0.0)
Requires-Dist: tqdm (>=4.66.1,<5.0.0)
Requires-Dist: typer (>=0.15.4,<0.16.0)
Requires-Dist: urllib3 (>=2.5.0,<3.0.0)
Project-URL: Homepage, https://celestical.eu
Project-URL: Repository, https://gitlab.com/parametry-ai/celestical/celestical
